sound_rs-0.1.5.dist-info/METADATA
sound_rs-0.1.5.dist-info/WHEEL
sound_rs/__init__.py
sound_rs/sound_rs.cp313-win_amd64.pyd
sound_rs-0.1.5.dist-info/RECORD
