Metadata-Version: 2.4
Name: sound_rs
Version: 0.1.5
Classifier: Programming Language :: Rust
Classifier: Programming Language :: Python :: Implementation :: CPython
Classifier: Programming Language :: Python :: Implementation :: PyPy
Summary: Fast Rust-powered audio playback library for Python
Requires-Python: >=3.7
Project-URL: Homepage, https://github.com/Neksand/sound_rs
Project-URL: Repository, https://github.com/Neksand/sound_rs
Project-URL: Issues, https://github.com/Neksand/sound_rs/issues
